INSTALL.rst
LICENSE
MANIFEST.in
README.rst
requirements.txt
setup.cfg
setup.py
tasks.py
src/ox/__init__.py
src/ox/automata.py
src/ox/helpers.py
src/ox/union.py
src/ox/utils.py
src/ox/backend/__init__.py
src/ox/backend/c/__init__.py
src/ox/backend/common/__init__.py
src/ox/backend/common/printers.py
src/ox/backend/javascript/__init__.py
src/ox/backend/python/__init__.py
src/ox/backend/python/ast_expr.py
src/ox/backend/python/ast_statement.py
src/ox/backend/python/ast_types.py
src/ox/backend/python/helpers.py
src/ox/backend/python/operators.py
src/ox/backend/python/parser.py
src/ox/backend/python/printers.py
src/ox/backend/python/utils.py
src/ox/examples/__init__.py
src/ox/examples/calculator.py
src/ox/examples/json.py
src/ox/lexer/__init__.py
src/ox/lexer/functions.py
src/ox/lexer/lexer.py
src/ox/lexer/utils.py
src/ox/parser/__init__.py
src/ox/parser/base.py
src/ox/parser/cli.py
src/ox/parser/ebnf.py
src/ox/parser/ebnf_expr.py
src/ox/parser/ply.py
src/ox/parser/utils.py
src/ox/regex/__init__.py
src/ox/regex/constants.py
src/ox/regex/functions.py
src/ox/regex/regex.py
src/ox_parser.egg-info/PKG-INFO
src/ox_parser.egg-info/SOURCES.txt
src/ox_parser.egg-info/dependency_links.txt
src/ox_parser.egg-info/not-zip-safe
src/ox_parser.egg-info/requires.txt
src/ox_parser.egg-info/top_level.txt